{
    "id": "ironmaninfamous",
    "name": "Iron Man (Infamous)",
    "abilityDetails": {
        "Cannot Crit": "Şampiyonun dövüş sırasında avantaj sağlayan özel Cannot Crit yeteneği.",
        "Shock": "Zamanla elektrik tabanlı şok hasarı verir.",
        "Energy Vulnerability": "Şampiyonun dövüş sırasında avantaj sağlayan özel Energy Vulnerability yeteneği.",
        "Armor Up": "Zırh değerini artırarak alınan fiziksel hasarı azaltır.",
        "Mid-Combo Stun": "Rakibi sersemleterek tamamen hareketsiz bırakır.",
        "Cowardice": "Şampiyonun dövüş sırasında avantaj sağlayan özel Cowardice yeteneği.",
        "Unblockable": "Saldırıların bloklanmasını engeller.",
        "Power Burn": "Şampiyonun dövüş sırasında avantaj sağlayan özel Power Burn yeteneği.",
        "Unstoppable": "Saldırılar sırasında sersemleme ve geri itilmeye karşı bağışıklık sağlar.",
        "Regeneration": "Can barını zamanla yeniler.",
        "Special Lock": "Şampiyonun dövüş sırasında avantaj sağlayan özel Special Lock yeteneği.",
        "Energize": "Şampiyonun dövüş sırasında avantaj sağlayan özel Energize yeteneği.",
        "Energy Resistance": "Şampiyonun dövüş sırasında avantaj sağlayan özel Energy Resistance yeteneği."
    },
    "synergies": [],
    "howToPlay": "Iron Man (Infamous) için oynanış rehberi: Özel saldırılarını kullanarak rakiplerini alt edin. Komboları düzgün zamanlayarak siper alın.",
    "bestUse": "Bu şampiyon genel maceralarda ve Tech sınıfı avantajı olan yollarda en iyi performansı gösterir.",
    "signatureAbility": "Iron Man (Infamous) Uyanış Yeteneği: İstatistikleri ve dövüş yeteneklerini güçlendirir."
}